{
  "foreclosures": {
    "last_run": "2026-07-21T15:04:28Z",
    "status": "success",
    "records_added": 3,
    "run_id": "29841969163",
    "run_url": "https://github.com/jfeelio/buying-hero-bot/actions/runs/29841969163"
  },
  "probate": {
    "last_run": "2026-04-13T15:04:22Z",
    "status": "success",
    "records_added": 4,
    "run_id": "24350517508",
    "run_url": "https://github.com/jfeelio/buying-hero-bot/actions/runs/24350517508"
  },
  "tax_deed": {
    "last_run": "2026-07-21T15:43:10Z",
    "status": "success",
    "records_added": 0,
    "run_id": "29845077726",
    "run_url": "https://github.com/jfeelio/buying-hero-bot/actions/runs/29845077726"
  }
}